{
    "scenarioName" : "corrupt_r2_r1_25",
    "logPath" : "/path/to/log_directory",
    "topo":"/path/to/topo.yaml",
    "data": "/path/to/data.json",

    "event":[
        {
            "beginTime" : 2,
            "type": "pumba",
            "host": "clab-bgp_features-r2",    
            "pumbaCommand": {
                "name" : "corrupt",
                "options":{
                    "percent" : 25, 
                    "duration": "300s",
                    "interface": "net0"
                }
            }
        },
        {
            "beginTime" : 2,
            "type": "pumba",
            "host": "clab-bgp_features-r2",    
            "pumbaCommand": {
                "name" : "corrupt",
                "options":{
                    "percent" : 25, 
                    "duration": "300s",
                    "interface": "net1"
                }
            }
        },
        {
            "beginTime" : 2,
            "type": "pumba",
            "host": "clab-bgp_features-r2",    
            "pumbaCommand": {
                "name" : "corrupt",
                "options":{
                    "percent" : 25, 
                    "duration": "300s",
                    "interface": "net2"
                }
            }
        },
        {
            "beginTime" : 2,
            "type": "pumba",
            "host": "clab-bgp_features-r2",    
            "pumbaCommand": {
                "name" : "corrupt",
                "options":{
                    "percent" : 25, 
                    "duration": "300s",
                    "interface": "net3"
                }
            }
        },
        {
            "beginTime" : 2,
            "type": "pumba",
            "host": "clab-bgp_features-r1",    
            "pumbaCommand": {
                "name" : "corrupt",
                "options":{
                    "percent" : 25, 
                    "duration": "300s",
                    "interface": "net0"
                }
            }
        },
        {
            "beginTime" : 2,
            "type": "pumba",
            "host": "clab-bgp_features-r1",    
            "pumbaCommand": {
                "name" : "corrupt",
                "options":{
                    "percent" : 25, 
                    "duration": "300s",
                    "interface": "net1"
                }
            }
        },
        {
            "beginTime" : 2,
            "type": "pumba",
            "host": "clab-bgp_features-r1",    
            "pumbaCommand": {
                "name" : "corrupt",
                "options":{
                    "percent" : 25, 
                    "duration": "300s",
                    "interface": "net2"
                }
            }
        },
        {
            "beginTime" : 2,
            "type": "pumba",
            "host": "clab-bgp_features-r1",    
            "pumbaCommand": {
                "name" : "corrupt",
                "options":{
                    "percent" : 25, 
                    "duration": "300s",
                    "interface": "net3"
                }
            }
        }
    ] 
}